setup.py
GitflowDennis.egg-info/PKG-INFO
GitflowDennis.egg-info/SOURCES.txt
GitflowDennis.egg-info/dependency_links.txt
GitflowDennis.egg-info/entry_points.txt
GitflowDennis.egg-info/requires.txt
GitflowDennis.egg-info/top_level.txt
dennis/__init__.py
dennis/console.py
dennis/tasks/__init__.py
dennis/tasks/prepare.py
dennis/tasks/release.py
dennis/tasks/task.py
dennis/tasks/utils.py