Metadata-Version: 1.0
Name: GitflowDennis
Version: 0.10.2
Summary: Dennis the release helper
Home-page: https://github.com/lystable/dennis
Author: Yannis Panousis
Author-email: yannis@lystable.com
License: MIT
Platform: UNKNOWN
